AgeXtend/AIM_D_Signaturizer_model_svm_HPTuned_fitted.pkl
AgeXtend/AgeXtend_BrowserOut.html
AgeXtend/BINDINGDB_MFPs.pkl
AgeXtend/BINDINGDB_db_MFPs.pkl
AgeXtend/BINDINGDB_db_MFPs_lb.pkl
AgeXtend/Browser.py
AgeXtend/HOLY_AIC_model_svm_HPTuned_fitted.pkl
AgeXtend/HOLY_AMES_model_MLP_HPTuned_fitted.pkl
AgeXtend/HOLY_BBB_model_MLPBoruta_HPTuned_fitted.pkl
AgeXtend/HOLY_CS_model_svm_HPTuned_fitted.pkl
AgeXtend/HOLY_CYP1A2_model_MLP_HPTuned_fitted.pkl
AgeXtend/HOLY_CYP2C19_model_SVM_HPTuned_fitted.pkl
AgeXtend/HOLY_CYP2C9_model_XGB_HPTuned_fitted.pkl
AgeXtend/HOLY_CYP2D6_model_SVM_HPTuned_fitted.pkl
AgeXtend/HOLY_CYP3A4_model_SVM_HPTuned_fitted.pkl
AgeXtend/HOLY_DILI_model_SVM_HPTuned_fitted.pkl
AgeXtend/HOLY_DNS_model_svm_HPTuned_fitted.pkl
AgeXtend/HOLY_EA_model_svm_HPTuned_fitted.pkl
AgeXtend/HOLY_GI_model_RF_HPTuned_fitted.pkl
AgeXtend/HOLY_HLM_model_XGB_HPTuned_fitted.pkl
AgeXtend/HOLY_Hepato_model_SVM_HPTuned_fitted.pkl
AgeXtend/HOLY_LP_model_svm_HPTuned_fitted.pkl
AgeXtend/HOLY_MD_model_XGB_HPTuned_fitted.pkl
AgeXtend/HOLY_MMP_model_XGB_HPTuned_fitted.pkl
AgeXtend/HOLY_MRTD_model_DTR_HPTuned_fitted.pkl
AgeXtend/HOLY_PGPInh_model_RF_HPTuned_fitted.pkl
AgeXtend/HOLY_PGPSub_model_SVM_HPTuned_fitted.pkl
AgeXtend/HOLY_SCE_model_et_HPTuned_fitted.pkl
AgeXtend/HOLY_TA_model_ET_HPTuned_fitted.pkl
AgeXtend/HOLY_hERG_model_SVM_HPTuned_fitted.pkl
AgeXtend/HallMark_Data_ECFPs.pkl
AgeXtend/Predictor.py
AgeXtend/__init__.py
AgeXtend/bindingdb_info.csv
AgeXtend/canage_predictions.csv
AgeXtend/canage_probabilities.csv
AgeXtend/hallmark_tanimoto_test.csv
AgeXtend/image1.png
AgeXtend/image2.png
AgeXtend/image3.png
AgeXtend/image4.png
AgeXtend/image5.png
AgeXtend/image6.png
AgeXtend/image7.png
AgeXtend/image8.png
AgeXtend/license.lic
AgeXtend/lipinsky_info.csv
AgeXtend-0.0.2.dist-info/LICENSE
AgeXtend-0.0.2.dist-info/METADATA
AgeXtend-0.0.2.dist-info/WHEEL
AgeXtend-0.0.2.dist-info/top_level.txt
AgeXtend-0.0.2.dist-info/RECORD
