Metadata-Version: 2.1
Name: AgeXtend
Version: 0.0.2
Summary: Discovering geroprotectors through the explainable artificial intelligence-based platform AgeXtend
Author: Sakshi Arora, Sanjay Kumar Mohanty
Author-email: sakshia@iiitd.ac.in, sanjaym@iiitd.ac.in
Classifier: Programming Language :: Python :: 3
Classifier: License :: OSI Approved :: MIT License
Classifier: Operating System :: OS Independent
Requires-Python: >=3.8
License-File: LICENSE
Requires-Dist: numpy
Requires-Dist: pandas
Requires-Dist: matplotlib
Requires-Dist: rdkit-pypi
Requires-Dist: scikit-learn
Requires-Dist: signaturizer
Requires-Dist: lime
Requires-Dist: joblib
Requires-Dist: importlib-resources
Requires-Dist: seaborn
Requires-Dist: xgboost
Requires-Dist: cloudpickle
